napari_manual_transforms/__init__.py
napari_manual_transforms/_model.py
napari_manual_transforms/_tform_widget.py
napari_manual_transforms/_util.py
napari_manual_transforms/_widget.py
napari_manual_transforms/napari.yaml
napari_manual_transforms-0.0.3.dist-info/LICENSE
napari_manual_transforms-0.0.3.dist-info/METADATA
napari_manual_transforms-0.0.3.dist-info/WHEEL
napari_manual_transforms-0.0.3.dist-info/entry_points.txt
napari_manual_transforms-0.0.3.dist-info/top_level.txt
napari_manual_transforms-0.0.3.dist-info/RECORD
