Metadata-Version: 2.1
Name: napari-manual-transforms
Version: 0.0.3
Summary: Interface to manually edit layer affine transforms
Home-page: https://github.com/tlambert03/napari-manual-transforms
Author: Talley Lambert
Author-email: talley.lambert@gmail.com
License: BSD-3-Clause
Project-URL: Bug Tracker, https://github.com/tlambert03/napari-manual-transforms/issues
Project-URL: Documentation, https://github.com/tlambert03/napari-manual-transforms#README.md
Project-URL: Source Code, https://github.com/tlambert03/napari-manual-transforms
Project-URL: User Support, https://github.com/tlambert03/napari-manual-transforms/issues
Platform: UNKNOWN
Classifier: Development Status :: 2 - Pre-Alpha
Classifier: Framework :: napari
Classifier: Intended Audience :: Developers
Classifier: License :: OSI Approved :: BSD License
Classifier: Operating System :: OS Independent
Classifier: Programming Language :: Python
Classifier: Programming Language :: Python :: 3
Classifier: Programming Language :: Python :: 3 :: Only
Classifier: Programming Language :: Python :: 3.8
Classifier: Programming Language :: Python :: 3.9
Classifier: Programming Language :: Python :: 3.10
Classifier: Topic :: Software Development :: Testing
Requires-Python: >=3.8
License-File: LICENSE
Requires-Dist: magicgui
Requires-Dist: napari
Requires-Dist: numpy
Requires-Dist: pytransform3d
Requires-Dist: qtpy
Requires-Dist: scipy
Requires-Dist: vispy
Provides-Extra: testing
Requires-Dist: napari ; extra == 'testing'
Requires-Dist: pyqt5 ; extra == 'testing'
Requires-Dist: pytest ; extra == 'testing'
Requires-Dist: pytest-cov ; extra == 'testing'
Requires-Dist: pytest-qt ; extra == 'testing'
Requires-Dist: tox ; extra == 'testing'
